idbsocialdatapy/__init__.py
idbsocialdatapy/core.py
idbsocialdatapy/metadata.py
idbsocialdatapy/utils.py
idbsocialdatapy-0.2.1.dist-info/METADATA
idbsocialdatapy-0.2.1.dist-info/WHEEL
idbsocialdatapy-0.2.1.dist-info/licenses/LICENSE.md
idbsocialdatapy-0.2.1.dist-info/RECORD
