Metadata-Version: 2.1
Name: idbsocialdatapy
Version: 0.2.1
Project-URL: Homepage, https://github.com/EL-BID/idbsocialdatapy
License-File: LICENSE.md
Requires-Python: >=3.7
Requires-Dist: pandas>=1.3.5
Provides-Extra: dev
Requires-Dist: autoflake>=1.7.7; extra == 'dev'
Requires-Dist: flake8>=5.0.4; extra == 'dev'
Requires-Dist: pre-commit>=2.20.0; extra == 'dev'
Requires-Dist: python-semantic-release>=7.32.2; extra == 'dev'
Provides-Extra: test
Requires-Dist: pytest>=7.2.0; extra == 'test'
